README
setup.cfg
setup.py
lelo/__init__.py
lelo/_lelo.py
lelo.egg-info/PKG-INFO
lelo.egg-info/SOURCES.txt
lelo.egg-info/dependency_links.txt
lelo.egg-info/entry_points.txt
lelo.egg-info/top_level.txt
lelo.egg-info/zip-safe