Metadata-Version: 1.0
Name: lelo
Version: 1.0rc2dev
Summary: Utilities for easy parallelisation of tasks
Home-page: https://bitbucket.org/jsbueno/lelo
Author: Joao S. O. Bueno
Author-email: jsbueno@simplesconsultoria.com.br
License: LGPLv3
Keywords: python parallel highperformance multicore core thread multithread python2
Platform: UNKNOWN
Classifier: Development Status :: 4 - Beta
Classifier: Environment :: No Input/Output (Daemon)
Classifier: Intended Audience :: Developers
Classifier: License :: OSI Approved :: GNU Lesser General Public License v3 or later (LGPLv3+)
Classifier: Operating System :: OS Independent
